{
    "$id": "https://commongateway.nl/schema/stuf.usedForEndpoint.schema.json",
    "$schema": "https://docs.commongateway.nl/schemas/Entity.schema.json",
    "version": "0.0.1",
    "type": "object",
    "title": "UsedForEndpoint",
    "description": "This schema only exists to link a endpoint to, nothing more.",
    "properties": {
        "thisSchema": {
          "type": "string"
        },
        "isUsed": {
          "type": "string"
        },
        "ForAnEndpoint": {
          "type": "string"
        }
    },
    "persist": false
}